django_napse/__init__.py
django_napse/api/__init__.py
django_napse/api/api_urls.py
django_napse/api/custom_permissions.py
django_napse/api/custom_viewset.py
django_napse/api/_utils/__init__.py
django_napse/api/_utils/template_messages.py
django_napse/api/bots/__init__.py
django_napse/api/bots/serializers/__init__.py
django_napse/api/bots/serializers/architecture_serializer.py
django_napse/api/bots/serializers/bot_serializers.py
django_napse/api/bots/serializers/config_serializer.py
django_napse/api/bots/serializers/plugin_serializer.py
django_napse/api/bots/serializers/strategy_serializer.py
django_napse/api/bots/views/__init__.py
django_napse/api/bots/views/bot_view.py
django_napse/api/exchanges/__init__.py
django_napse/api/exchanges/serializers/__init__.py
django_napse/api/exchanges/serializers/exchange_account_detail_serializer.py
django_napse/api/exchanges/serializers/exchange_account_serializer.py
django_napse/api/exchanges/views/__init__.py
django_napse/api/exchanges/views/exchange_account_view.py
django_napse/api/fleets/__init__.py
django_napse/api/fleets/serializers/__init__.py
django_napse/api/fleets/serializers/cluster_serialisers.py
django_napse/api/fleets/serializers/fleet_serializers.py
django_napse/api/fleets/views/__init__.py
django_napse/api/fleets/views/fleet_view.py
django_napse/api/histories/__init__.py
django_napse/api/histories/serializers/__init__.py
django_napse/api/histories/serializers/datapoint.py
django_napse/api/histories/serializers/datapoint_field.py
django_napse/api/histories/serializers/history.py
django_napse/api/keys/__init__.py
django_napse/api/keys/serializers/__init__.py
django_napse/api/keys/serializers/key.py
django_napse/api/keys/views/__init__.py
django_napse/api/keys/views/key_view.py
django_napse/api/orders/__init__.py
django_napse/api/orders/serializers/__init__.py
django_napse/api/orders/serializers/order_serializer.py
django_napse/api/orders/views/__init__.py
django_napse/api/orders/views/order_view.py
django_napse-1.13.8.dist-info/LICENSE
django_napse-1.13.8.dist-info/METADATA
django_napse-1.13.8.dist-info/WHEEL
django_napse-1.13.8.dist-info/top_level.txt
django_napse-1.13.8.dist-info/RECORD
