Metadata-Version: 2.1
Name: django-napse
Version: 1.13.8
Summary: The heart and brains of the Napse Invest platform.
Home-page: https://github.com/napse-invest/django-napse
Download-URL: https://github.com/napse-invest/django-napse/archive/refs/tags/vv1.13.8.tar.gz
Author: Napse Invest
Author-email: napse.invest@gmail.com
License: MIT
Keywords: Investing,Django,Trading
Classifier: Development Status :: 4 - Beta
Classifier: Intended Audience :: Developers
Classifier: Topic :: Software Development :: Build Tools
Classifier: License :: OSI Approved :: MIT License
Classifier: Programming Language :: Python :: 3.11
License-File: LICENSE
Requires-Dist: django >=4.2
Requires-Dist: django-environ >=0.10
Requires-Dist: django-celery-beat >=2.5
Requires-Dist: drf-spectacular >=0.26
Requires-Dist: django-cors-headers >=4.2
Requires-Dist: djangorestframework-api-key >=2.3.0
Requires-Dist: psycopg2-binary >=2.9
Requires-Dist: celery >=5.3
Requires-Dist: redis >=5.0
Requires-Dist: python-binance >=1
Requires-Dist: pandas >=2
Requires-Dist: pydantic >=2.6
